{
  "info": {
    "name": "Kabby Admin API",
    "description": "API endpoints for the Kabby Admin mobile app integration",
    "schema": "https://schema.getpostman.com/json/collection/v2.1.0/collection.json"
  },
  "item": [
    {
      "name": "Banners",
      "item": [
        {
          "name": "Get Active Banners",
          "request": {
            "method": "GET",
            "header": [],
            "url": {
              "raw": "{{base_url}}/api/banners",
              "host": ["{{base_url}}"],
              "path": ["api", "banners"]
            },
            "description": "Get a list of all active banners sorted by priority order"
          },
          "response": []
        }
      ],
      "description": "Banner-related API endpoints"
    }
  ],
  "variable": [
    {
      "key": "base_url",
      "value": "http://localhost:8000",
      "type": "string"
    }
  ]
} 